{"version": "1", "message": "ERROR: Hidden Testcases server unreachable.", "problem_id": "ads2_m1_a1_1", "user_id": "Mounika2010", "score": {"sample": {"0": {"execution_time": 0.22367095947265625, "passed": true}, "1": {"execution_time": 0.20010876655578613, "passed": true}, "2": {"execution_time": 0.43959736824035645, "passed": false}, "3": {"execution_time": 0.20731067657470703, "passed": true}, "4": {"execution_time": 0.2110748291015625, "passed": true}, "5": {"execution_time": 0.20469951629638672, "passed": true}, "6": {"execution_time": 0.17631125450134277, "passed": true}, "7": {"execution_time": 0.22678446769714355, "passed": true}}}, "check_style_score": "1/1"}